LICENSE
MANIFEST.in
README.md
setup.py
examples/__init__.py
examples/repository.py
examples/users.py
pyolite/__init__.py
pyolite/git.py
pyolite/patterns.py
pyolite/pyolite.py
pyolite/repo.py
pyolite.egg-info/PKG-INFO
pyolite.egg-info/SOURCES.txt
pyolite.egg-info/dependency_links.txt
pyolite.egg-info/requires.txt
pyolite.egg-info/top_level.txt
pyolite/managers/__init__.py
pyolite/managers/manager.py
pyolite/managers/repository.py
pyolite/managers/user.py
pyolite/models/__init__.py
pyolite/models/repository.py
pyolite/models/user.py
pyolite/models/lists/__init__.py
pyolite/models/lists/keys.py
pyolite/models/lists/users.py
tests/__init__.py
tests/mocked_manager.py
tests/test_git.py
tests/test_pyolite.py
tests/test_repo.py
tests/integrations/__init__.py
tests/lists/__init__.py
tests/lists/test_keys.py
tests/lists/test_users.py
tests/managers/__init__.py
tests/managers/test_manager.py
tests/managers/test_repository.py
tests/managers/test_user.py
tests/models/__init__.py
tests/models/test_repository.py
tests/models/test_user.py