Metadata-Version: 1.1
Name: pyolite
Version: 1.6
Summary: Python wrapper for gitolite
Home-page: https://github.com/Presslabs/pyolite
Author: Vlad Temian
Author-email: vlad@presslabs.com
License: UNKNOWN
Platform: any
Classifier: Development Status :: 5 - Production/Stable
Classifier: Intended Audience :: Developers
Classifier: Intended Audience :: System Administrators
Classifier: License :: OSI Approved :: BSD License
Classifier: Operating System :: MacOS :: MacOS X
Classifier: Operating System :: Microsoft :: Windows
Classifier: Operating System :: POSIX
Classifier: Topic :: System :: Networking
Classifier: Programming Language :: Python :: 2.7
Classifier: Programming Language :: Python :: 3.5
